{
  "cardsExcelFile": "Cards.xlsx",
  "bossesExcelFile": "Bosses.xlsx",
  "enemyNamesExcelFile": "EnemyNames.xlsx",
  "mapConfigs": [
    {
      "width": 7,
      "height": 15,
      "pathDensity": 16,
      "campsiteFrequency": 0.175,
      "mysteryFrequency": 0.2,
      "eliteFrequency": 0.2
    },
    {
      "width": 7,
      "height": 15,
      "pathDensity": 16,
      "campsiteFrequency": 0.175,
      "mysteryFrequency": 0.2,
      "eliteFrequency": 0.2
    },
    {
      "width": 7,
      "height": 15,
      "pathDensity": 16,
      "campsiteFrequency": 0.175,
      "mysteryFrequency": 0.2,
      "eliteFrequency": 0.2
    }
  ],
  "normalEnemyConfig": {
    "baseHealth": 50,
    "baseManna": 0,
    "baseDeckSize": 20,
    "baseTradeRowSize": 3,
    "baseHandSize": 5,
    "minCardCost": 0,
    "maxCardCost": 7
  },
  "eliteEnemyConfig": {
    "baseHealth": 75,
    "baseManna": 0,
    "baseDeckSize": 17,
    "baseTradeRowSize": 4,
    "baseHandSize": 5,
    "minCardCost": 4,
    "maxCardCost": 8
  },
  "playerConfig": {
    "health": 25,
    "vision": 10,
    "awareness": 7,
    "insight": 3,
    "tradeRowSize": 3,
    "manna": 0,
    "handSize": 5
  },
  "initialCardSelections": [
    {
      "minCost": 1,
      "maxCost": 4,
      "cardCount": 2
    },
    {
      "minCost": 1,
      "maxCost": 4,
      "cardCount": 3
    },
    {
      "minCost": 1,
      "maxCost": 4,
      "cardCount": 4
    }
  ],
  "journeyLength": 3
}